{"ApprovalTime": "2016-03-13T21:25:27Z", "AutoApprovalTime": "2016-03-13T21:25:22Z", "AssignmentId": "3OVR4I9USPJFELMBJM1W8UN31XUQ4J", "WorkerId": "anon42", "answers": {"data": [{"start_number": 269, "digits": "266\n263\n260\n257\n254\n251\n248", "B_Recall": "bike\ntree\ninsect", "save_choice": "delete", "word_condition": 8, "FileB": "bikes,hate,waste,lip,form,jeans,match,rat", "FileA": "bear,insect,dinner,crib,hobby,thumb,knot,blade", "time": 111219, "A_Recall": "chain\n", "save_condition": "nosave"}, {"start_number": 680, "digits": "677\n674\n671\n668", "B_Recall": "doll\nskate\ntoad\n", "save_choice": "save", "word_condition": 8, "FileB": "cannon,zoo,attack,brick,plate,crown,cat,board", "FileA": "doll,skate,toad,collar,powder,sense,shoe,system", "time": 123039, "A_Recall": "doll\nskate\ntoad\npowder\n", "save_condition": "save"}, {"start_number": 813, "digits": "810\n807\n804\n801\n798", "B_Recall": "moth\nsteel\n", "save_choice": "delete", "word_condition": 8, "FileB": "moth,steel,lumber,suit,sound,trip,sign,junk", "FileA": "top,animal,stream,test,meat,chair,store,bead", "time": 105783, "A_Recall": "note", "save_condition": "nosave"}, {"start_number": 256, "digits": "253\n250\n247\n244\n241", "B_Recall": "spice\nclam\noil", "save_choice": "delete", "word_condition": 8, "FileB": "horse,space,cent,meal,candy,army,expert,wash", "FileA": "clam,mice,guide,key,note,river,pen,earth", "time": 103469, "A_Recall": "oil\noyster\nsky", "save_condition": "nosave"}, {"start_number": 211, "digits": "218\n215\n212\n209\n206", "B_Recall": "stage\ntoy", "save_choice": "save", "word_condition": 8, "FileB": "toy,glove,roll,scene,fowl,lace,son,field", "FileA": "stage,duck,rifle,fang,shirt,bulb,fruit,yarn", "time": 119627, "A_Recall": "stage\nduck\nrifle\nfang\nshirt", "save_condition": "save"}, {"start_number": 946, "digits": "943\n940\n937\n934\n931\n928\n9", "B_Recall": "file\nletter\ntub\ncellar\nshirt\n", "save_choice": "save", "word_condition": 8, "FileB": "title,tub,letter,cellar,offer,planes,knee,hope", "FileA": "chess,curtain,time,plant,pies,geese,jar,word", "time": 116682, "A_Recall": "chess\ncurtain\ntime\nplant", "save_condition": "save"}, {"start_number": 379, "digits": "376\n373\n370\n367\n364", "B_Recall": "shirt\n", "save_choice": "save", "word_condition": 8, "FileB": "laugh,whip,land,thing,car,walk,sink,camp", "FileA": "cup,street,paper,bank,voyage,fuel,swing,bag", "time": 119664, "A_Recall": "cup\nstreet\npaper\nbank", "save_condition": "save"}, {"start_number": 793, "digits": "790\n787\n784\n781\n778\n775\n7", "B_Recall": "star\nshine\n", "save_choice": "delete", "word_condition": 8, "FileB": "top,animal,stream,test,meat,chair,store,bead", "FileA": "flag,eggs,boy,rail,party,snow,button,wine", "time": 100452, "A_Recall": "oil\nship", "save_condition": "nosave"}, {"comment": "", "gender": "male", "age": "30", "race": "white", "homelang": "english"}]}, "AcceptTime": "2016-03-13T20:42:53Z", "HITId": "3L84EBDQ372BU0FQ16ZEU544PVSKKO", "Assignment": "", "AssignmentStatus": "Approved", "SubmitTime": "2016-03-13T21:20:22Z"}